casement/__init__.py
casement/__main__.py
casement/app_id.py
casement/cli.py
casement/enums.py
casement/env_var.py
casement/registry.py
casement/shortcut.py
casement/utils.py
casement/version.py
casement-0.4.0.dist-info/licenses/LICENSE
casement-0.4.0.dist-info/METADATA
casement-0.4.0.dist-info/WHEEL
casement-0.4.0.dist-info/entry_points.txt
casement-0.4.0.dist-info/top_level.txt
casement-0.4.0.dist-info/RECORD
