Metadata-Version: 2.4
Name: casement
Version: 0.4.0
Summary: Useful functionality for managing Microsoft Windows.
Author-email: Blur Studio <opensource@blur.com>
License: LGPL-3.0
Project-URL: Homepage, https://github.com/blurstudio/casement
Project-URL: Source, https://github.com/blurstudio/casement
Project-URL: Issues, https://github.com/blurstudio/casement/issues
Platform: any
Classifier: Development Status :: 3 - Alpha
Classifier: Environment :: Console
Classifier: Intended Audience :: Developers
Classifier: Operating System :: Microsoft
Classifier: Operating System :: Microsoft :: Windows :: Windows 7
Classifier: Operating System :: Microsoft :: Windows :: Windows 10
Classifier: Programming Language :: Python
Classifier: Programming Language :: Python :: 3
Classifier: Programming Language :: Python :: 3 :: Only
Classifier: Programming Language :: Python :: Implementation :: CPython
Classifier: Programming Language :: Python :: Implementation :: PyPy
Requires-Python: >=3.7
License-File: LICENSE
Requires-Dist: pywin32
Requires-Dist: six
Requires-Dist: winshell>=0.6
Provides-Extra: dev
Requires-Dist: black==22.12.0; extra == "dev"
Requires-Dist: covdefaults; extra == "dev"
Requires-Dist: coverage; extra == "dev"
Requires-Dist: flake8==5.0.4; extra == "dev"
Requires-Dist: flake8-bugbear==23.3.12; extra == "dev"
Requires-Dist: Flake8-pyproject; extra == "dev"
Requires-Dist: pep8-naming==0.13.3; extra == "dev"
Requires-Dist: pytest; extra == "dev"
Requires-Dist: tox; extra == "dev"
Provides-Extra: pil
Requires-Dist: Pillow; extra == "pil"
Dynamic: license-file
